{
  "updated": "2026-04-15 13:44 UTC",
  "items": [
    {
      "title": "Blue Origin has a new employee stock plan, but not everyone is happy",
      "url": "https://arstechnica.com/space/2026/04/blue-origin-has-a-new-employee-stock-plan-but-not-everyone-is-happy/",
      "source": "Ars Technica",
      "affiliate": false
    },
    {
      "title": "It's Tax Day, and no one knows how to file for prediction market winnings",
      "url": "https://arstechnica.com/tech-policy/2026/04/its-tax-day-and-no-one-knows-how-to-file-for-prediction-market-winnings/",
      "source": "Ars Technica",
      "affiliate": false
    },
    {
      "title": "More phone cameras should come with telephoto lenses",
      "url": "https://www.theverge.com/tech/912097/vivo-x300-ultra-camera-kit-hands-on",
      "source": "The Verge",
      "affiliate": false
    },
    {
      "title": "Adobe embraces conversational AI editing, marking a ‘fundamental shift’ in creative work",
      "url": "https://www.theverge.com/tech/912287/adobe-firefly-ai-assistant-announcement-editing",
      "source": "The Verge",
      "affiliate": false
    },
    {
      "title": "Amazon’s new Fire TV Stick HD is its ‘slimmest ever’",
      "url": "https://www.theverge.com/tech/912346/amazon-fire-tv-stick-hd-slimmest-ever",
      "source": "The Verge",
      "affiliate": false
    },
    {
      "title": "Nothing makes it easy to share files between any Android phone and a Mac",
      "url": "https://www.theverge.com/tech/912317/nothing-warp-android-mac-pc-linux-hands-on",
      "source": "The Verge",
      "affiliate": false
    },
    {
      "title": "The new Tomodachi Life is made to be shared — even if Nintendo doesn’t want you to",
      "url": "https://www.theverge.com/entertainment/911950/tomodachi-life-living-the-dream-review-nintendo-switch",
      "source": "The Verge",
      "affiliate": false
    },
    {
      "title": "Microsoft faces fresh Windows Recall security concerns",
      "url": "https://www.theverge.com/report/912101/microsoft-windows-recall-new-security-concerns-response",
      "source": "The Verge",
      "affiliate": false
    }
  ]
}
